{
  "id": "2bb8a895-0d49-48b2-99f0-13f65c2eef98",
  "title": "Converstar AI Review: Does This AI Tool Really Boost Website Conversions?",
  "url": "https://dev.to/honest_app/converstar-ai-review-does-this-ai-tool-really-boost-website-conversions-i5l",
  "date": "2026-04-26T12:00:39Z",
  "content": "Your website gets visitors. But they leave without buying anything. This happens every single day. You are losing money and you do not even know why.\n\nConverstar AI says it can fix this. It is an AI tool that tries to turn visitors into customers. You add one piece of code to your site. The AI then tries to engage people at the right time. Let's see if it works.\n\n## What is Converstar AI?\n\nConverstar AI is a cloud-based software tool. You install it with a small JavaScript snippet. This code goes in the header section of your website. It works on any platform that lets you add custom code.\n\nOnce installed, it loads in your visitor's browser. The tool watches how people behave on your site. It uses simple rules and timing. For example, it can see if someone is about to leave the page.\n\nIt then shows a targeted message. This could be a pop-up, a notification bar, or a coupon offer. The goal is to get the visitor to take action before they go.\n\nThe system runs in the cloud. You manage everything from an online dashboard. You do not need to host anything on your own server. You create campaigns in the dashboard. These campaigns are then delivered to your visitors automatically.\n\nThe logic is based on common conversion tactics. It uses timers, scroll depth, and exit intent. Exit intent tries to guess when a mouse is moving to close the browser tab. It is not perfect magic, but it is effective.\n\nThe AI label refers to its automated optimization. The system can test different messages against each other. It learns which one gets more clicks or sign-ups. It then shows the winning version more often. This is basic A/B testing, automated.\n\n[Check out the Converstar AI Stack](https://launchpadjv.com/o/277/2834)\n\n## The Technical Breakdown\n\nThis tool is built for people who are not developers. But it has useful features for tech-savvy builders too. It saves time by automating repetitive website optimization tasks.\n\n### Campaign Builder & Logic Engine\n\nYou build campaigns in a visual editor. It is a drag-and-drop interface. You choose a campaign type like a pop-up or a notification bar.\n\nYou set the triggers. A trigger is the rule for when it appears. You can set it to show after a 10-second delay. Or show it when someone scrolls 60% down the page. You can also target it to exit intent.\n\nThe logic engine handles the rules. You can show different campaigns to different visitors. For example, you can show a special offer to new visitors only. You can show a thank you message to returning customers.\n\n✅ Saves hours of manual coding for pop-ups and modals.\n✅ Centralized dashboard to manage all site messages in one place.\n✅ Allows for complex audience targeting without writing rules from scratch.\n✅ The A/B testing runs automatically, finding what works best for you.\n\n### Real-Time Social Proof Notifications\n\nThis feature shows small messages on your site. They update in real time. A message might say \"Someone from Chicago just bought Product X.\" This is meant to build trust and urgency.\n\nThe system pulls data from your site's conversion events. You need to set up a simple webhook or use their provided pixel. When a purchase or sign-up happens, the system is notified. It then broadcasts a fake-name version of that event to other visitors.\n\nThe API here is straightforward. You send a POST request to their endpoint with basic event data. Their system handles name generation, location, and timing. It is a set-it-and-forget-it social proof engine.\n\n✅ Creates automatic social validation without manual updates.\n✅ The simple API can connect to most e-commerce platforms or form tools.\n✅ Drives perceived value and can reduce customer hesitation.\n✅ Works 24/7, simulating a busy, popular store even when you are asleep.\n\n### Lead Capture & Data Export\n\nThis is a core function. Converstar AI can collect email addresses and other lead data. It uses the pop-ups and notification bars you design.\n\nAll captured lead data feeds into the cloud dashboard. You can view it, filter it, and download it as a CSV file. This lets you import leads into your email service provider or CRM.\n\nThere are also native notification handlers. You can get an instant alert on Slack, email, or WhatsApp when a lead comes in. This is great for time-sensitive businesses like consulting.\n\n✅ Automates the lead collection process across your entire site.\n✅ Exports clean CSV data ready for other systems, saving manual data entry.\n✅ Instant alerts mean you can follow up with hot leads immediately, which boosts sales.\n✅ Consolidates leads from multiple site forms into one simple report.\n\n### The Commercial License & White-Label Potential\n\nThis is a big feature for agencies and freelancers. The commercial license lets you use Converstar AI on client websites. You can charge for setting it up and managing it.\n\nThe dashboard is not fully white-label. Clients will still see the Converstar AI branding unless you buy the separate \"Branding Freedom\" upgrade. This is a common upsell in the funnel.\n\nThe workflow is efficient. You can manage multiple client sites from a single dashboard. You can deploy the same proven campaign templates across all your clients in minutes.\n\n✅ Creates a new service offering you can sell to existing website clients.\n✅ Centralized management saves enormous time compared to tools per client.\n✅ Lets you package conversion rate optimization as a recurring service.\n✅ Simple deployment (one code snippet) makes client onboarding very fast.\n\n[Deploy Converstar AI for your workflow](https://launchpadjv.com/o/277/2834)\n\n## Technical Trade-offs & Limitations\n\nNo tool is perfect. Converstar AI makes trade-offs for ease of use. You need to know its limits before you buy.\n\nIt is a cloud-dependent service. If their servers have a problem, your campaigns stop working. Your website will still function, but the pop-ups and notifications will not show up.\n\n❌ The tool requires a stable internet connection for your visitors. It adds a small external JavaScript file to your site's loading chain.\n❌ The \"AI\" is primarily automated A/B testing. Do not expect deep, predictive machine learning.\n❌ Advanced users will find the API limited. It is good for sending conversion events in, but not for pulling complex data out.\n❌ The visual builder is simple, which is good. But it lacks the deep customization of a full-code solution. Your designs might look generic.\n\n## Who Is This Stack For?\n\nThis tool fits specific types of builders and business owners.\n\n👉 **The Busy Solopreneur:** You run a small e-commerce store or blog. You know you need pop-ups and email collectors, but you lack time to code and test them. Converstar AI lets you set up proven campaigns in an afternoon. It then runs and optimizes them.\n\n👉 **The Marketing Agency Owner:** You manage websites for local businesses or niche brands. You need a standard, reliable tool for conversion boosts that you can deploy quickly. The commercial license lets you add this as a service package. You save time using one dashboard for all clients.\n\n👉 **The Non-Technical Content Creator:** You have an audience and a website, but technical stuff scares you. You just want to add an email signup bar without hiring a developer. The one-line code install and visual editor are made for you.\n\n## Pricing & The Funnel\n\nThe pricing has a front-end offer and several upsells. You must understand what you are getting.\n\nThe **Front-End Offer ($16.99 one-time)** gets you the core Converstar AI Premium. This includes use on 1 website, all core campaign types, and basic notifications. It is a lifetime deal, which is good value compared to monthly fees.\n\nThen come the upsells (OTOs):\n\n*   **OTO 1: Unlimited ($67 one-time):** Use it on unlimited websites. This is essential for agencies or anyone with more than one site.\n*   **OTO 2: Automation Expansion ($97 one-time):** Adds automated email follow-up sequences and more advanced A/B testing.\n*   **OTO 3: Done-For-You Setup ($197 one-time):** Their team installs and configures everything for you.\n*   **OTO 4: Agency Teams ($197 one-time):** Adds team member seats and client management features.\n*   **OTO 5: Branding Freedom ($97 one-time):** Removes Converstar AI branding from the widgets on your site.\n\nThe core front-end product is useful. The unlimited upgrade is a must-buy for serious users. Evaluate the other upsells based on your specific needs.\n\n[See the Full Converstar AI Pricing](https://launchpadjv.com/o/277/2834)\n\n## Tech Comparison\n\nHow does it stack up against other options? Here is a simple table.\n\n| Feature | Converstar AI | OptinMonster (Mainstream Alternative) | Fully Custom-Coded Solution |\n| :--- | :--- | :--- | :--- |\n| **Cost Model** | Lifetime deal (front-end) | High monthly subscription | Large upfront dev cost |\n| **Ease of Setup** | Very easy, one code snippet | Easy, often has plugins | Difficult, requires a developer |\n| **Customization** | Good, within template limits | Very good | Unlimited, fully custom |\n| **Automated A/B Testing** | Yes, basic | Yes, more advanced | Must be built manually |\n| **Ownership & Portability** | Cloud service, you depend on them | Cloud service, you depend on them | You own everything |\n| **Best For** | Budget-focused users, agencies starting out | Large budgets, WordPress-heavy shops | Large companies with specific, complex needs |\n\n## Final Verdict\n\nThis is a **Buy** for the right person.\n\nThe value is in automation and time savings. The lifetime deal price for the core product is low risk. If you hate manually building and testing pop-ups, this tool will save you 10+ hours immediately.\n\nThe ROI is clear. If one extra email signup or sale per week pays for the $16.99, it is worth it. For agencies, the commercial license is a no-brainer to streamline client services.\n\n**Pass if** you need deep, custom-coded interactions or you cannot stand adding another external script to your site. **Pass if** you expect true, advanced artificial intelligence.\n\nFor most website owners who want a simple, set-and-forget conversion tool, Converstar AI works. It packages standard best practices into an affordable, automated system.\n\nStop letting visitors slip away. Get a system that works to convert them around the clock.\n\n[Get Converstar AI at the lifetime deal price before it's gone](https://launchpadjv.com/o/277/2834)",
  "source": "devto",
  "tags": "review, software"
}
