{
  "id": "743e6c9e-14c6-4b29-a7d9-72338003c339",
  "title": "The Python return Statement: Usage and Best Practices",
  "url": "https://realpython.com/python-return-statement/",
  "date": "",
  "content": "— FREE Email Series — 🐍 Python Tricks 💌  🔒 No spam. Unsubscribe any time. Table of Contents Recommended Course Using the Python return Statement Effectively 1h 30m · 22 lessons Table of Contents Recommended Course Using the Python return Statement Effectively(1h 30m) The Pythonreturnstatementis a special statement that you can use inside afunctionormethodto send the function’s result back to the caller. Areturnstatement consists of thereturnkeyword followed by an optionalreturn value. The return value of a Python function can be any Python object, and you can use them to perform further computation in your programs. Using thereturnstatement effectively is a core skill if you want to code custom functions that arePythonicand robust. In this tutorial, you’ll learn that: With this knowledge, you’ll be able to write more readable, maintainable, and concise functions in Python. If you’re totally new to Python functions, then you can check outDefining Your Own Python Functionbefore diving into this tutorial. Free Bonus:5 Thoughts On Python Mastery, a free course for Python developers that shows you the roadmap and the mindset you’ll need to take your Python skills to the next level. Take the Quiz:Test your knowledge with our interactive “The Python return Statement” quiz. You’ll receive a score upon completion to help you track your learning progress: Interactive Quiz In this quiz, you can practice your understanding of how to use the Python return statement when writing functions. Additionally, you'll cover some good programming practices related to the use of return. With this knowledge, you'll be able to write readable, robust, and maintainable functions in Python. Most programming languages allow you to assign a name to a code block that performs a concrete computation. These named code blocks can be reused quickly because you can use their name to call them from different places in your code. Programmers call these named code blockssubroutines,routines,procedures, orfunctionsdepending on the language they use. In some languages, there’s a clear difference between a routine or procedure and a function. Sometimes that difference is so strong that you need to use a specific keyword to define a procedure or subroutine and another keyword to define a function. For example theVisual Basicprogramming language usesSubandFunctionto differentiate between the two. In general, aprocedureis a named code block that performs a set of actions without computing a final value or result. On the other hand, afunctionis a named code block that performs some actions with the purpose of computing a final value or result, which is then sent back to the caller code. Both procedures and functions can act upon a set ofinput values, commonly known asarguments. In Python, these kinds of named code blocks are known asfunctionsbecause they always send a value back to the caller. The Python documentation defines a function as follows: A series of statements which returns some value to a caller. It can also be passed zero or moreargumentswhich may be used in the execution of the body. (Source) Even though the official documentation states that a function “returns some value to the caller,” you’ll soon see that functions can return any Python object to the caller code. In general, a functiontakesarguments (if any),performssome operations, andreturnsa value (or object). The value that a function returns to the caller is generally known as the function’sreturn value. All Python functions have a return value, either explicit or implicit. You’ll cover the difference between explicit and implicit return values later in this tutorial. To write a Python function, you need aheaderthat starts with thedefkeyword, followed by the name of the function, an optional list of comma-separated arguments inside a required pair of parentheses, and a final colon. The second component of a function is itscode block, orbody. Python defines code blocks usingindentationinstead of brackets,beginandendkeywords, and so on. So, to define a function in Python you can use the following syntax: When you’re coding a Python function, you need to define a header with thedefkeyword, the name of the function, and a list of arguments in parentheses. Note that the list of arguments is optional, but the parentheses are syntactically required. Then you need to define the function’s code block, which will begin one level of indentation to the right. In the above example, you use apassstatement. This kind of statement is useful when you need a placeholder statement in your code to make it syntactically correct, but you don’t need to perform any action.passstatements are also known as thenull operationbecause they don’t perform any action. Note:The full syntax to define functions and their arguments is beyond the scope of this tutorial. For an in-depth resource on this topic, check outDefining Your Own Python Function. To use a function, you need to call it. A function call consists of the function’s name followed by the function’s arguments in parentheses: You’ll need to pass arguments to a function call only if the function requires them. The parentheses, on the other hand, are always required in a function call. If you forget them, then you won’t be calling the function but referencing it as a function object. To make your functions return a value, you need to use thePythonreturnstatement. That’s what you’ll cover from this point on. ThePythonreturnstatementis a special statement that you can use inside a function ormethodto send the function’s result back to the caller. Areturnstatement consists of thereturnkeywordfollowed by an optionalreturn value. The return value of a Python function can be any Python object. Everything in Python is an object. So, your functions can return numeric values (int,float, andcomplexvalues), collections and sequences of objects (list,tuple,dictionary, orsetobjects), user-defined objects, classes, functions, and evenmodules or packages. You can omit the return value of a function and use a barereturnwithout a return value. You can also omit the entirereturnstatement. In both cases, the return value will beNone. In the next two sections, you’ll cover the basics of how thereturnstatement works and how you can use it to return the function’s result back to the caller code. Anexplicitreturnstatementimmediately terminates a function execution and sends the return value back to the caller code. To add an explicitreturnstatement to a Python function, you need to usereturnfollowed by an optional return value: When you definereturn_42(), you add an explicitreturnstatement (return 42) at the end of the function’s code block.42is the explicit return value ofreturn_42(). This means that any time you callreturn_42(), the function will send42back to the caller. Note:You can use explicitreturnstatements with or without a return value. If you build areturnstatement without specifying a return value, then you’ll be implicitly returningNone. If you define a function with an explicitreturnstatement that has an explicit return value, then you can use that return value in any expression: Sincereturn_42()returns a numeric value, you can use that value in a math expression or any other kind of expression in which the value has a logical or coherent meaning. This is how a caller code can take advantage of a function’s return value. Note that you can use areturnstatement only inside a function or method definition. If you use it anywhere else, then you’ll get aSyntaxError: When you usereturnoutside a function or method, you get aSyntaxErrortelling you that the statement can’t be used outside a function. Note:Regular methods, class methods, and static methodsare just functions within the context ofPython classes. So, all thereturnstatement concepts that you’ll cover apply to them as well. You can use any Python object as a return value. Since everything in Python is an object, you can returnstrings, lists, tuples, dictionaries, functions,classes, instances, user-defined objects, and even modules or packages. For example, say you need to write a function that takes a list of integers and returns a list containing only the even numbers in the original list. Here’s a way of coding this function: get_even()uses alist comprehensionto create a list that filters out the odd numbers in the originalnumbers. Then the function returns the resulting list, which contains only even numbers. A common practice is to use the result of anexpressionas a return value in areturnstatement. To apply this idea, you can rewriteget_even()as follows: The list comprehension gets evaluated and then the function returns with the resulting list. Note that you can only useexpressionsin areturnstatement. Expressions are different fromstatementslikeconditionalsorloops. Note:Even thoughlistcomprehensions are built usingforand (optionally)ifkeywords, they’re considered expressions rather than statements. That’s why you can use them in areturnstatement. For a further example, say you need to calculate the mean of a sample of numeric values. To do that, you need to divide the sum of the values by the number of values. Here’s an example that uses the built-in functionssum()andlen(): Inmean(), you don’t use a localvariableto store the result of the calculation. Instead, you use the expression directly as a return value. Python first evaluates the expressionsum(sample) / len(sample)and then returns the result of the evaluation, which in this case is the value2.5. A Python function will always have a return value. There is no notion of procedure or routine in Python. So, if you don’t explicitly use a return value in areturnstatement, or if you totally omit thereturnstatement, then Python will implicitly return a default value for you. That default return value will always beNone. Say you’re writing a function that adds1to a numberx, but you forget to supply areturnstatement. In this case, you’ll get animplicitreturnstatementthat usesNoneas a return value: If you don’t supply an explicitreturnstatement with an explicit return value, then Python will supply an implicitreturnstatement usingNoneas a return value. In the above example,add_one()adds1toxand stores the value inresultbut it doesn’t returnresult. That’s why you getvalue = Noneinstead ofvalue = 6. To fix the problem, you need to eitherreturn resultor directlyreturn x + 1. An example of a function that returnsNoneisprint(). The goal of this function is to print objects to a text stream file, which is normally the standard output (your screen). So, this function doesn’t need an explicitreturnstatement because it doesn’t return anything useful or meaningful: The call toprint()printsHello, Worldto the screen. Since this is the purpose ofprint(), the function doesn’t need to return anything useful, so you getNoneas a return value. Note:ThePython interpreterdoesn’t displayNone. So, to show a return value ofNonein aninteractive session, you need to explicitly useprint(). Regardless of how long and complex your functions are, any function without an explicitreturnstatement, or one with areturnstatement without a return value, will returnNone. If you’re working in an interactive session, then you might think that printing a value and returning a value are equivalent operations. Consider the following two functions and their output: Both functions seem to do the same thing. In both cases, you seeHello, Worldprinted on your screen. There’s only a subtle visible difference—the single quotation marks in the second example. But take a look at what happens if you return another data type, say anintobject: There’s no visible difference now. In both cases, you can see42on your screen. That behavior can be confusing if you’re just starting with Python. You might think that returning and printing a value are equivalent actions. Now, suppose you’re getting deeper into Python and you’re starting to write your first script. You open a text editor and type the following code: add()takes two numbers, adds them, and returns the result. Online 5, you calladd()to sum2plus2. Since you’re still learning the difference between returning and printing a value, you might expect your script to print4to the screen. However, that’s not what happens, and you get nothing on your screen. Try it out by yourself. Save your script to a file calledadding.pyandrun it from your command lineas follows: If you runadding.pyfrom your command line, then you won’t see any result on your screen. That’s because when you run a script, the return values of the functions that you call in the script don’t get printed to the screen like they do in an interactive session. If you want that your script to show the result of callingadd()on your screen, then you need to explicitly callprint(). Check out the following update ofadding.py: Now, when you runadding.py, you’ll see the number4on your screen. So, if you’re working in an interactive session, then Python will show the result of any function call directly to your screen. But if you’re writing a script and you want to see a function’s return value, then you need to explicitly useprint(). You can use areturnstatement to return multiple values from a function. To do that, you just need to supply several return values separated by commas. For example, suppose you need to write a function that takes a sample of numeric data and returns a summary of statistical measures. To code that function, you can use the Python standard modulestatistics, which provides several functions for calculating mathematical statistics of numeric data. Here’s a possible implementation of your function: Indescribe(), you take advantage of Python’s ability to return multiple values in a singlereturnstatement by returning the mean, median, and mode of the sample at the same time. Note that, to return multiple values, you just need to write them in a comma-separated list in the order you want them returned. Note:If your functions needs several different return types, then you’re dealing with a more complex scenario. In this case, you can get some help fromHow to Use Type Hints for Multiple Return Types in Python. Once you’ve codeddescribe(), you can take advantage of a powerful Python feature known asiterable unpackingto unpack the three measures into three separatedvariables, or you can just store everything in one variable: Here, you unpack the three return values ofdescribe()into the variablesmean,median, andmode. Note that in the last example, you store all the values in a single variable,desc, which turns out to be a Pythontuple. Note:You can build a Pythontupleby justassigningseveral comma-separated values to a single variable. There’s no need to use parentheses to create atuple. That’s why multiple return values are packed in atuple. The built-in functiondivmod()is also an example of a function that returns multiple values. The function takes two (non-complex) numbers as arguments and returns two numbers, the quotient of the two input values and the remainder of the division: The call todivmod()returns a tuple containing the quotient and remainder that result from dividing the two non-complex numbers provided as arguments. This is an example of a function with multiple return values. So far, you’ve covered the basics of how the Pythonreturnstatement works. You now know how to write functions that return one or multiple values to the caller. Additionally, you’ve learned that if you don’t add an explicitreturnstatement with an explicit return value to a given function, then Python will add it for you. That value will beNone. In this section, you’ll cover several examples that will guide you through a set of good programming practices for effectively using thereturnstatement. These practices will help you to write more readable, maintainable, robust, and efficient functions in Python. Some programmers rely on the implicitreturnstatement that Python adds to any function without an explicit one. This can be confusing for developers who come from other programming languages in which a function without a return value is called aprocedure. There are situations in which you can add an explicitreturn Noneto your functions. In other situations, however, you can rely on Python’s default behavior: If your function performs actions but doesn’t have a clear and usefulreturnvalue, then you can omit returningNonebecause doing that would just be superfluous and confusing. You can also use a barereturnwithout a return value just to make clear your intention of returning from the function. If your function has multiplereturnstatements and returningNoneis a valid option, then you should consider the explicit use ofreturn Noneinstead of relying on the Python’s default behavior. These practices can improve the readability and maintainability of your code by explicitly communicating your intent. When it comes to returningNone, you can use one of three possible approaches: Here’s how this works in practice: Whether or not to returnNoneexplicitly is a personal decision. However, you should consider that in some cases, an explicitreturn Nonecan avoid maintainability problems. This is especially true for developers who come from other programming languages that don’t behave like Python does. When writing custom functions, you might accidentally forget to return a value from a function. In this case, Python will returnNonefor you. This can cause subtle bugs that can be difficult for a beginning Python developer tounderstand and debug. You can avoid this problem by writing thereturnstatement immediately after the header of the function. Then you can make a second pass to write the function’s body. Here’s a template that you can use when coding your Python functions: If you get used to starting your functions like this, then chances are that you’ll no longer miss thereturnstatement. With this approach, you can write the body of the function, test it, and rename the variables once you know that the function works. This practice can increase your productivity and make your functions less error-prone. It can also save you a lot ofdebuggingtime. As you saw before, it’s a common practice to use the result of an expression as a return value in Python functions. If the expression that you’re using gets too complex, then this practice can lead to functions that are difficult to understand, debug, and maintain. For example, if you’re doing a complex calculation, then it would be more readable to incrementally calculate the final result usingtemporary variableswith meaningful names. Consider the following function that calculates thevarianceof a sample of numeric data: The expression that you use here is quite complex and difficult to understand. It’s also difficult to debug because you’re performing multiple operations in a single expression. To work around this particular problem, you can take advantage of an incremental development approach that improves the readability of the function. Take a look at the following alternative implementation ofvariance(): In this second implementation ofvariance(), you calculate the variance in several steps. Each step is represented by a temporary variable with a meaningful name. Temporary variables liken,mean, andtotal_square_devare often helpful when it comes to debugging your code. If, for example, something goes wrong with one of them, then you can callprint()to know what’s happening before thereturnstatement runs. In general, you should avoid using complex expressions in yourreturnstatement. Instead, you can break your code into multiple steps and use temporary variables for each step. Using temporary variables can make your code easier to debug, understand, and maintain. Functions that don’t have an explicitreturnstatement with a meaningful return value often preform actions that haveside effects. Aside effectcan be, for example, printing something to the screen, modifying aglobal variable, updating the state of an object,writing some text to a file, and so on. Modifying global variables is generally considered a bad programming practice. Just like programs with complex expressions, programs that modify global variables can be difficult to debug, understand, and maintain. When you modify a global variable, you’re potentially affecting all the functions, classes, objects, and any other parts of your programs that rely on that global variable. To understand a program that modifies global variables, you need to be aware of all the parts of the program that can see, access, and change those variables. So, good practice recommends writingself-contained functionsthat take some arguments and return a useful value (or values) without causing any side effect on global variables. Additionally, functions with an explicitreturnstatement that return a meaningful value are easier totestthan functions that modify or update global variables. The following example show a function that changes a global variable. The function uses theglobalstatement, which is also considered a bad programming practice in Python: In this example, you first create a global variable,counter, with an initial value of0. Insideincrement(), you use aglobalstatement to tell the function that you want to modify a global variable. The last statement incrementscounterby1. The result of callingincrement()will depend on the initial value ofcounter. Different initial values forcounterwill generate different results, so the function’s result can’t be controlled by the function itself. To avoid this kind of behavior, you can write a self-containedincrement()that takes arguments and returns a coherent value that depends only on the input arguments: Now the result of callingincrement()depends only on the input arguments rather than on the initial value ofcounter. This makes the function more robust and easier to test. Note:For a better understanding of how to test your Python code, check outTest-Driven Development With PyTest. If you’d like a deeper dive into using global variables in functions, thenUsing and Creating Global Variables in Your Python Functionsis for you. Additionally, when you need to updatecounter, you can do so explicitly with a call toincrement(). This way, you’ll have more control over what’s happening withcounterthroughout your code. In general, it’s a good practice to avoid functions that modify global variables. If possible, try to writeself-contained functionswith an explicitreturnstatement that returns a coherent and meaningful value. Python functions are not restricted to having a singlereturnstatement. If a given function has more than onereturnstatement, then the first one encountered will determine the end of the function’s execution and also its return value. A common way of writing functions with multiplereturnstatements is to useconditional statementsthat allow you to provide differentreturnstatements depending on the result of evaluating some conditions. Suppose you need to code a function that takes a number and returns itsabsolute value. If the number is greater than0, then you’ll return the same number. If the number is less than0, then you’ll return its opposite, or non-negative value. Here’s a possible implementation for this function: my_abs()has two explicitreturnstatements, each of them wrapped in its ownifstatement. It also has an implicitreturnstatement. Ifnumberhappens to be0, then neither condition is true, and the function ends without hitting any explicitreturnstatement. When this happens, you automatically getNone. Take a look at the following call tomy_abs()using0as an argument: When you callmy_abs()using0as an argument, you getNoneas a result. That’s because the flow of execution gets to the end of the function without reaching any explicitreturnstatement. Unfortunately, the absolute value of0is0, notNone. To fix this problem, you can add a thirdreturnstatement, either in a newelifclause or in a finalelseclause: Now,my_abs()checks every possible condition,number > 0,number < 0, andnumber == 0. The purpose of this example is to show that when you’re using conditional statements to provide multiplereturnstatements, you need to make sure that every possible option gets its ownreturnstatement. Otherwise, your function will have a hidden bug. Finally, you can implementmy_abs()in a more concise, efficient, andPythonicway using a singleifstatement: In this case, your function hits the firstreturnstatement ifnumber < 0. In all other cases, whethernumber > 0ornumber == 0, it hits the secondreturnstatement. With this new implementation, your function looks a lot better. It’s more readable, concise, and efficient. Note:There’s a convenient built-in Python function calledabs()for computing the absolute value of a number. The function in the above example is intended only to illustrate the point under discussion. If you’re usingifstatements to provide severalreturnstatements, then you don’t need anelseclause to cover the last condition. Just add areturnstatement at the end of the function’s code block and at the first level of indentation. Another common use case for the combination ofifandreturnstatements is when you’re coding apredicateorBoolean-valuedfunction. This kind of function returns eitherTrueorFalseaccording to a given condition. For example, say you need to write a function that takes two integers,aandb, and returnsTrueifais divisible byb. Otherwise, the function should returnFalse. Here’s a possible implementation: is_divisible()returnsTrueif the remainder of dividingabybis equal to0. Otherwise, it returnsFalse. Note that in Python, a0value isfalsy, so you need to use thenotoperatorto negate the truth value of the condition. Sometimes you’ll write predicate functions that involve operators like the following: In these cases, you can directly use aBoolean expressionin yourreturnstatement. This is possible because these operators return eitherTrueorFalse. Following this idea, here’s a new implementation ofis_divisible(): Ifais divisible byb, thena % breturns0, which is falsy in Python. So, to returnTrue, you need to use thenotoperator. Note:Python follows a set of rules to determine the truth value of an object. For example, the following objects areconsidered falsy: Any other object will be considered truthy. On the other hand, if you try to use conditions that involve Boolean operators likeorandandin the way you saw before, then your predicate functions won’t work correctly. That’s because these operators behave differently. They return one of the operands in the condition rather thanTrueorFalse: In general,andreturns the first false operand or the last operand. On the other hand,orreturns the first true operand or the last operand. So, to write a predicate that involves one of these operators, you’ll need to use an explicitifstatement or a call to the built-in functionbool(). Suppose you want to write a predicate function that takes two values and returnsTrueif both are true andFalseotherwise. Here’s your first approach to this function: Sinceandreturns operands instead ofTrueorFalse, your function doesn’t work correctly. There are at least three possibilities for fixing this problem: If you use the first approach, then you can writeboth_true()as follows: Theifstatement checks ifaandbare both truthy. If so, thenboth_true()returnsTrue. Otherwise, it returnsFalse. If, on the other hand, you use a Python conditional expression or ternary operator, then you can write your predicate function as follows: Here, you use a conditional expression to provide a return value forboth_true(). The conditional expression is evaluated toTrueif bothaandbare truthy. Otherwise, the final result isFalse. Finally, if you usebool(), then you can codeboth_true()as follows: bool()returnsTrueifaandbare true andFalseotherwise. It’s up to you what approach to use for solving this problem. However, the second solution seems more readable. What do you think? Areturnstatement inside a loop performs some kind ofshort-circuit. It breaks the loop execution and makes the function return immediately. To better understand this behavior, you can write a function that emulatesany(). This built-in function takes an iterable and returnsTrueif at least one of its items is truthy. To emulateany(), you can code a function like the following: If anyiteminiterableis true, then the flow of execution enters in theifblock. Thereturnstatement breaks the loop and returns immediately with a return value ofTrue. If no value initerableis true, thenmy_any()returnsFalse. This function implements ashort-circuit evaluation. For example, suppose that you pass an iterable that contains a million items. If the first item in that iterable happens to be true, then the loop runs only one time rather than a million times. This can save you a lot of processing time when running your code. It’s important to note that to use areturnstatement inside a loop, you need to wrap the statement in anifstatement. Otherwise, the loop will always break in its first iteration. As soon as a function hits areturnstatement, it terminates without executing any subsequent code. Consequently, the code that appears after the function’sreturnstatement is commonly calleddead code. The Python interpreter totally ignores dead code when running your functions. So, having that kind of code in a function is useless and confusing. Consider the following function, which adds code after itsreturnstatement: The statementprint(\"Hello, World\")in this example will never execute because that statement appears after the function’sreturnstatement. Identifying dead code and removing it is a good practice that you can apply to write better functions. It’s worth noting that if you’re using conditional statements to provide multiplereturnstatements, then you can have code after areturnstatement that won’t be dead as long as it’s outside theifstatement: Even though the call toprint()is after areturnstatement, it’s not dead code. Whenconditionis evaluated toFalse, theprint()call is run and you getHello, Worldprinted to your screen. When you’re writing a function that returns multiple values in a singlereturnstatement, you can consider using acollections.namedtupleobject to make your functions more readable.namedtupleis a collection class that returns a subclass oftuplethat has fields or attributes. You can access those attributes usingdot notationor anindexing operation. The initializer ofnamedtupletakes several arguments. However, to start usingnamedtuplein your code, you just need to know about the first two: Using anamedtuplewhen you need to return multiple values can make your functions significantly more readable without too much effort. Consider the following update ofdescribe()using anamedtupleas a return value: Insidedescribe(), you create anamedtuplecalledDesc. This object can have named attributes that you can access by using dot notation or by using an indexing operation. In this example, those attributes are\"mean\",\"median\", and\"mode\". You can create aDescobject and use it as a return value. To do that, you need to instantiateDesclike you’d do with any Python class. Note that you need to supply a concrete value for each named attribute, just like you did in yourreturnstatement. Here’s howdescribe()works now: When you calldescribe()with a sample of numeric data, you get anamedtupleobject containing the mean, median, and mode of the sample. Note that you can access each element of the tuple by using either dot notation or an indexing operation. Finally, you can also use an iterable unpacking operation to store each value in its own independent variable. In Python, functions arefirst-class objects. A first-class object is an object that can be assigned to a variable, passed as an argument to a function, or used as a return value in a function. So, you can use a function object as a return value in anyreturnstatement. A function that takes a function as an argument, returns a function as a result, or both is ahigher-order function. Aclosure factory functionis a common example of a higher-order function in Python. This kind of function takes some arguments and returns aninner function. The inner function is commonly known as aclosure. A closure carries information about its enclosing execution scope. This provides a way to retain state information between function calls. Closure factory functions are useful when you need to write code based on the concept oflazy or delayed evaluation. Suppose you need to write a helper function that takes a number and returns the result of multiplying that number by a given factor. You can code that function as follows: by_factor()takesfactorandnumberas arguments and returns their product. Sincefactorrarely changes in your application, you find it annoying to supply the same factor in every function call. So, you need a way to retain the state or value offactorbetween calls toby_factor()and change it only when needed. To retain the current value offactorbetween calls, you can use a closure. The following implementation ofby_factor()uses a closure to retain the value offactorbetween calls: Insideby_factor(), you define an inner function calledmultiply()and return it without calling it. The function object you return is a closure that retains information about the state offactor. In other words, it remembers the value offactorbetween calls. That’s whydoubleremembers thatfactorwas equal to2andtripleremembers thatfactorwas equal to3. Note that you can freely reusedoubleandtriplebecause they don’t forget their respective state information. You can also use alambdafunctionto create closures. Sometimes the use of alambdafunction can make your closure factory more concise. Here’s an alternative implementation ofby_factor()using alambdafunction: This implementation works just like the original example. In this case, the use of alambdafunction provides a quick and concise way to codeby_factor(). Another way of using thereturnstatement for returning function objects is to writedecorator functions. Adecorator functiontakes a function object as an argument and returns a function object. The decorator processes the decorated function in some way and returns it or replaces it with another function or callable object. Decorators are useful when you need to add extra logic to existing functions without modifying them. For example, you can code a decorator to log function calls, validate the arguments to a function, measure the execution time of a given function, and so on. The following example shows a decorator function that you can use to get an idea of the execution time of a given Python function: The syntax@my_timerabove the header ofdelayed_mean()is equivalent to the expressiondelayed_mean = my_timer(delayed_mean). In this case, you can say thatmy_timer()is decoratingdelayed_mean(). Python runs decorator functions as soon as youimportor run a module or a script. So, when you calldelayed_mean(), you’re really calling the return value ofmy_timer(), which is the function object_timer. The call to the decorateddelayed_mean()will return the mean of the sample and will also measure the execution time of the originaldelayed_mean(). In this case, you usetime()to measure the execution time inside the decorator.time()lives in a module calledtimethat provides a set of time-related functions.time()returns the time in seconds since theepochas a floating-point number. The difference between the time before and after the call todelayed_mean()will give you an idea of the function’s execution time. Note:Indelayed_mean(), you use the functiontime.sleep(), which suspends the execution of the calling code for a given number of seconds. For a better understanding on how to usesleep(), check outPython sleep(): How to Add Time Delays to Your Code. Other common examples of decorators in Python areclassmethod(),staticmethod(), andproperty(). If you want to dive deeper into Python decorators, then take a look atPrimer on Python Decorators. You can also check outPython Decorators 101. The Pythonreturnstatement can also returnuser-defined objects. In other words, you can use your own custom objects as a return value in a function. A common use case for this capability is thefactory pattern. The factory pattern defines an interface for creating objects on the fly in response to conditions that you can’t predict when you’re writing a program. You can implement a factory of user-defined objects using a function that takes some initialization arguments and returns different objects according to the concrete input. Say you’re writing a painting application. You need to create different shapes on the fly in response to your user’s choices. Your program will have squares, circles, rectangles, and so on. To create those shapes on the fly, you first need to create the shape classes that you’re going to use: Once you have a class for each shape, you can write a function that takes the name of the shape as a string and an optional list ofarguments (*args) and keyword arguments (**kwargs)to create and initialize shapes on the fly: This function creates an instance of the concrete shape and returns it to the caller. Now you can useshape_factory()to create objects of different shapes in response to the needs of your users: If you callshape_factory()with the name of the required shape as a string, then you get a new instance of the shape that matches theshape_nameyou’ve just passed to the factory. When you use areturnstatement inside atrystatementwith afinallyclause, thatfinallyclause is always executed before thereturnstatement. This ensures that the code in thefinallyclause will always run. Check out the following example: When you callfunc(), you getvalueconverted to a floating-point number or a string object. Before doing that, your function runs thefinallyclause and prints a message to your screen. Whatever code you add to thefinallyclause will be executed before the function runs itsreturnstatement. A Python function with ayieldstatementin its body is agenerator function. When you call a generator function, it returns agenerator iterator. So, you can say that a generator function is agenerator factory. You can use areturnstatement inside a generator function to indicate that the generator is done. Thereturnstatement will make the generator raise aStopIteration. The return value will be passed as an argument to the initializer ofStopIterationand will be assigned to its.valueattribute. Here’s a generator that yields1and2on demand and then returns3: gen()returns a generator object that yields1and2on demand. To retrieve each number form the generator object, you can usenext(), which is a built-in function that retrieves the next item from a Python generator. The first two calls tonext()retrieve1and2, respectively. In the third call, the generator is exhausted, and you get aStopIteration. Note that the return value of the generator function (3) becomes the.valueattribute of theStopIterationobject. The Pythonreturnstatement allows you to send any Python object from yourcustom functionsback to the caller code. This statement is a fundamental part of any Python function or method. If you master how to use it, then you’ll be ready to code robust functions. Next, you’ll find common questions that sum up the most important concepts you’ve learned in this tutorial. You can use these questions to check, recap, and solidify your knowledge. After each question, you’ll find an answer hidden in a collapsible section. Click theShow/Hidetoggle to reveal it. But first, try to come up with the answer on your own. What’s the difference between explicit and implicit return statements?Show/Hide An explicitreturnstatement immediately ends the function’s execution and sends the specified value back to the caller. For example, a function can return a number, a list, or any other object. If no return statement is present, Python adds one implicitly, which returnsNone. How do I return single or multiple values from my functions to the caller code?Show/Hide In Python, thereturnstatement allows you to send values back to the caller from a function. To return a single value, use thereturnkeyword followed by the value. This can be any data type, such as a number, string, list, or object. To return multiple values, list them after the return keyword separated by commas. Python packs these values into a tuple. You can then unpack the tuple into separate variables or store it as a single variable. What are the best practices I should apply when using the return statement?Show/Hide First, explicitly returnNonewhen appropriate. If your function should returnNone, do so explicitly withreturn Nonefor clarity. However, if your function performs actions without a clear return value, you can omit thereturnstatement and rely on Python implicitly returningNone. Additionally, avoid complex return expressions. Instead, break them down to improve readability and debugging. You can also use short-circuiting in loops to simplify your code. Employreturnstatements inside loops to exit early when a condition is met, saving processing time. You should also prefer self-contained functions over those that modify global variables, and when using conditional returns, handle all possible conditions with appropriate return statements to avoid hidden bugs. How do I code a closure factory function?Show/Hide Creating aclosure factory functioninvolves making a function that returns another function. This inner function retains access to the variables from the outer function. It’s perfect for situations where you want to keep some state information between calls. How do I code a decorator function?Show/Hide Fordecorator functions, you write a function that takes another function, adds some extra functionality, and returns this new function. Decorators are great for tasks like logging and timing that aren’t central to the original function’s purpose. Do you want to take a quick quiz to evaluate your new skills? If so, then click the link below: Take the Quiz:Test your knowledge with our interactive “The Python return Statement” quiz. You’ll receive a score upon completion to help you track your learning progress: Interactive Quiz In this quiz, you can practice your understanding of how to use the Python return statement when writing functions. Additionally, you'll cover some good programming practices related to the use of return. With this knowledge, you'll be able to write readable, robust, and maintainable functions in Python. Recommended Course Using the Python return Statement Effectively(1h 30m) 🐍 Python Tricks 💌 Get a short & sweetPython Trickdelivered to your inbox every couple of days. No spam ever. Unsubscribe any time. Curated by the Real Python team. AboutLeodanis Pozo Ramos Leodanis is a self-taught Python developer, educator, and technical writer with over 10 years of experience. Each tutorial at Real Python is created by a team of developers so that it meets our high quality standards. The team members who worked on this tutorial are: Aldren Bryan Brenda Geir Arne Joanna Jacob MasterReal-World Python SkillsWith Unlimited Access to Real Python  Join us and get access to thousands of tutorials, hands-on video courses, and a community of expert Pythonistas: Level Up Your Python Skills » MasterReal-World Python SkillsWith Unlimited Access to Real Python  Join us and get access to thousands of tutorials, hands-on video courses, and a community of expert Pythonistas: Level Up Your Python Skills » What Do You Think? What’s your #1 takeaway or favorite thing you learned? How are you going to put your newfound skills to use? Leave a comment below and let us know. Commenting Tips:The most useful comments are those written with the goal of learning from or helping out other students.Get tips for asking good questionsandget answers to common questions in our support portal.Looking for a real-time conversation? Visit theReal Python Community Chator join the next“Office Hours” Live Q&A Session. Happy Pythoning! Keep Learning Related Topics:basicsbest-practicespython Related Learning Paths: Related Courses: Related Tutorials: Continue » Already have an account?Sign-In Almost there! Complete this form and click the button below to gain instant access: 5 Thoughts On Python Mastery 🔒 No spam. We take your privacy seriously. ",
  "source": "realpython",
  "tags": []
}